msaf/__init__.py
msaf/base.py
msaf/configdefaults.py
msaf/configparser.py
msaf/eval.py
msaf/exceptions.py
msaf/features.py
msaf/input_output.py
msaf/plotting.py
msaf/run.py
msaf/utils.py
msaf/version.py
msaf/algorithms/__init__.py
msaf/algorithms/interface.py
msaf/algorithms/cnmf/__init__.py
msaf/algorithms/cnmf/config.py
msaf/algorithms/cnmf/segmenter.py
msaf/algorithms/example/__init__.py
msaf/algorithms/example/config.py
msaf/algorithms/example/segmenter.py
msaf/algorithms/fmc2d/__init__.py
msaf/algorithms/fmc2d/config.py
msaf/algorithms/fmc2d/segmenter.py
msaf/algorithms/fmc2d/utils_2dfmc.py
msaf/algorithms/fmc2d/xmeans.py
msaf/algorithms/foote/__init__.py
msaf/algorithms/foote/config.py
msaf/algorithms/foote/segmenter.py
msaf/algorithms/olda/OLDA.py
msaf/algorithms/olda/__init__.py
msaf/algorithms/olda/config.py
msaf/algorithms/olda/fit_olda_model.py
msaf/algorithms/olda/make_train.py
msaf/algorithms/olda/segmenter.py
msaf/algorithms/olda/models/EstBeats_BeatlesIso.npy
msaf/algorithms/olda/models/EstBeats_BeatlesTUT.npy
msaf/algorithms/olda/models/EstBeats_SALAMI-i.npy
msaf/algorithms/scluster/__init__.py
msaf/algorithms/scluster/config.py
msaf/algorithms/scluster/main2.py
msaf/algorithms/scluster/segmenter.py
msaf/algorithms/sf/__init__.py
msaf/algorithms/sf/config.py
msaf/algorithms/sf/segmenter.py
msaf/algorithms/vmo/__init__.py
msaf/algorithms/vmo/config.py
msaf/algorithms/vmo/main.py
msaf/algorithms/vmo/segmenter.py
msaf/pymf/__init__.py
msaf/pymf/aa.py
msaf/pymf/bnmf.py
msaf/pymf/chnmf.py
msaf/pymf/cmd.py
msaf/pymf/cmeans.py
msaf/pymf/cnmf.py
msaf/pymf/cur.py
msaf/pymf/cursl.py
msaf/pymf/dist.py
msaf/pymf/gmap.py
msaf/pymf/greedy.py
msaf/pymf/greedycur.py
msaf/pymf/kmeans.py
msaf/pymf/laesa.py
msaf/pymf/nmf.py
msaf/pymf/nmfals.py
msaf/pymf/nmfnnls.py
msaf/pymf/nndsvd.py
msaf/pymf/pca.py
msaf/pymf/rnmf.py
msaf/pymf/sivm.py
msaf/pymf/sivm_cur.py
msaf/pymf/sivm_gsat.py
msaf/pymf/sivm_search.py
msaf/pymf/sivm_sgreedy.py
msaf/pymf/snmf.py
msaf/pymf/sub.py
msaf_test-0.1.70.dist-info/AUTHORS.md
msaf_test-0.1.70.dist-info/LICENSE.md
msaf_test-0.1.70.dist-info/METADATA
msaf_test-0.1.70.dist-info/WHEEL
msaf_test-0.1.70.dist-info/top_level.txt
msaf_test-0.1.70.dist-info/RECORD
